pymsys/__init__.py
pymsys/child_list.py
pymsys/helpers.py
pymsys/link.py
pymsys/metadata.py
pymsys/server.py
pymsys/connectables/__init__.py
pymsys/connectables/connectable.py
pymsys/generators/__init__.py
pymsys/generators/counter_generator.py
pymsys/generators/generator.py
pymsys/generators/uuid_generator.py
pymsys/interfaces/__init__.py
pymsys/interfaces/igenerator.py
pymsys/interfaces/ilink.py
pymsys/interfaces/imetadata.py
pymsys/interfaces/iserializer.py
pymsys/interfaces/ivalue.py
pymsys/nodes/__init__.py
pymsys/nodes/example.py
pymsys/nodes/node.py
pymsys/options/__init__.py
pymsys/options/option.py
pymsys/scripts/__init__.py
pymsys/values/__init__.py
pymsys/values/value.py
pymsys-0.0.3.dist-info/METADATA
pymsys-0.0.3.dist-info/WHEEL
pymsys-0.0.3.dist-info/entry_points.txt
pymsys-0.0.3.dist-info/top_level.txt
pymsys-0.0.3.dist-info/RECORD
